jupyterlab_poul_theme/__init__.py
jupyterlab_poul_theme/_version.py
jupyterlab_poul_theme-0.0.2.data/data/share/jupyter/labextensions/jupyterlab-poul-theme/package.json
jupyterlab_poul_theme-0.0.2.data/data/share/jupyter/labextensions/jupyterlab-poul-theme/static/509.8eb9cf3486981ddfa8ad.js
jupyterlab_poul_theme-0.0.2.data/data/share/jupyter/labextensions/jupyterlab-poul-theme/static/remoteEntry.c280bf41e5ef60195058.js
jupyterlab_poul_theme-0.0.2.data/data/share/jupyter/labextensions/jupyterlab-poul-theme/static/style.js
jupyterlab_poul_theme-0.0.2.data/data/share/jupyter/labextensions/jupyterlab-poul-theme/static/third-party-licenses.json
jupyterlab_poul_theme-0.0.2.data/data/share/jupyter/labextensions/jupyterlab-poul-theme/themes/jupyterlab-poul-theme/index.css
jupyterlab_poul_theme-0.0.2.data/data/share/jupyter/labextensions/jupyterlab-poul-theme/themes/jupyterlab-poul-theme/index.js
jupyterlab_poul_theme-0.0.2.data/data/share/jupyter/labextensions/jupyterlab-poul-theme/install.json
jupyterlab_poul_theme-0.0.2.dist-info/METADATA
jupyterlab_poul_theme-0.0.2.dist-info/WHEEL
jupyterlab_poul_theme-0.0.2.dist-info/licenses/LICENSE
jupyterlab_poul_theme-0.0.2.dist-info/RECORD
