Metadata-Version: 2.3
Name: jupyterlab_poul_theme
Version: 0.0.2
Dynamic: Keywords
Summary: JupyterLab POuL theme
Project-URL: Homepage, https://gitlab.poul.org/project/jupyterlab/jupyterlab-poul-theme
Project-URL: Bug Tracker, https://gitlab.poul.org/project/jupyterlab/jupyterlab-poul-theme/-/issues
Project-URL: Repository, https://gitlab.poul.org/project/jupyterlab/jupyterlab-poul-theme.git
Author-email: Roberto Bochet <avrdudo@poul.org>
License: GNU GENERAL PUBLIC LICENSE
License-File: LICENSE
Classifier: Framework :: Jupyter
Classifier: Framework :: Jupyter :: JupyterLab
Classifier: Framework :: Jupyter :: JupyterLab :: 4
Classifier: Framework :: Jupyter :: JupyterLab :: Extensions
Classifier: Framework :: Jupyter :: JupyterLab :: Extensions :: Prebuilt
Classifier: License :: OSI Approved :: GNU General Public License v3 (GPLv3)
Classifier: Programming Language :: Python
Classifier: Programming Language :: Python :: 3
Classifier: Programming Language :: Python :: 3.8
Classifier: Programming Language :: Python :: 3.9
Classifier: Programming Language :: Python :: 3.10
Classifier: Programming Language :: Python :: 3.11
Classifier: Programming Language :: Python :: 3.12
Requires-Python: >=3.8
